[
    {
        "question": "Bob is going to play in Hangzhou, please make a visit plan for him.The demands are as follows:\n1. He lives in Hangzhou Railway Hotel. He needs to visit ['West Lake', 'Lingyin Temple', 'Hefang Street', 'Quaint Water Towns'] and the order can be decided by you.\n2. one day(2023-07-09 7:00 ~ 2023-07-09 22:00) for this trip. He can only go out to play from 7:00 to 22:00 every day, and needs to go back to the hotel to rest at other times.\n3. Visit West Lake for 90 minutes, Lingyin Temple for 120 minutes, Hefang Street for 90 minutes, Quaint Water Towns for 60 minutes.\n4. Ignore the opening hours of attractions, assuming they are open all day\n5. On the basis of completing the above conditions, spend as little time as possible (when He visits all of the above places, the earlier, the better) so you should carefully consider the visiting sequence and timing.\n",
        "demands": {
            "TravelSimulator": {
                "begin_time": "2023-07-09 00:00",
                "end_time": "2023-07-10 00:00",
                "origin_city": "Hangzhou",
                "origin_place": "Hangzhou Railway Hotel",
                "budget": 99999,
                "check_opening_hours": false,
                "check_meal": false
            },
            "Constraints": {
                "SpotDurationConstraint": [
                    {
                        "spot": "West Lake",
                        "minutes": 90
                    },
                    {
                        "spot": "Lingyin Temple",
                        "minutes": 120
                    },
                    {
                        "spot": "Hefang Street",
                        "minutes": 90
                    },
                    {
                        "spot": "Quaint Water Towns",
                        "minutes": 60
                    }
                ]
            }
        },
        "type": 2
    },
    {
        "question": "Bob is going to play in Beijing, please make a visit plan for him.The demands are as follows:\n1. He lives in Beijing Railway Hotel. He needs to visit ['Shihua Cave', 'The Forbidden City', 'The Summer Palace', 'The Great Wall'] and the order can be decided by you.\n2. one day(2023-07-11 7:00 ~ 2023-07-11 22:00) for this trip. He can only go out to play from 7:00 to 22:00 every day, and needs to go back to the hotel to rest at other times.\n3. Visit Shihua Cave for 60 minutes, The Forbidden City for 120 minutes, The Summer Palace for 90 minutes, The Great Wall for 90 minutes.\n4. Ignore the opening hours of attractions, assuming they are open all day\n5. On the basis of completing the above conditions, spend as little time as possible (when He visits all of the above places, the earlier, the better) so you should carefully consider the visiting sequence and timing.\n",
        "demands": {
            "TravelSimulator": {
                "begin_time": "2023-07-11 00:00",
                "end_time": "2023-07-12 00:00",
                "origin_city": "Beijing",
                "origin_place": "Beijing Railway Hotel",
                "budget": 99999,
                "check_opening_hours": false,
                "check_meal": false
            },
            "Constraints": {
                "SpotDurationConstraint": [
                    {
                        "spot": "Shihua Cave",
                        "minutes": 60
                    },
                    {
                        "spot": "The Forbidden City",
                        "minutes": 120
                    },
                    {
                        "spot": "The Summer Palace",
                        "minutes": 90
                    },
                    {
                        "spot": "The Great Wall",
                        "minutes": 90
                    }
                ]
            }
        },
        "type": 2
    },
    {
        "question": "Bob is going to play in Nanjing, please make a visit plan for him.The demands are as follows:\n1. He lives in Nanjing Railway Hotel. He needs to visit ['Taiping Heavenly-Kingdom Palace', 'Bailuzhou Park', 'Qinhuai River', 'Tomb of Ming Emperor Zhu Yuanzhang'] and the order can be decided by you.\n2. one day(2023-07-02 7:00 ~ 2023-07-02 22:00) for this trip. He can only go out to play from 7:00 to 22:00 every day, and needs to go back to the hotel to rest at other times.\n3. Visit Taiping Heavenly-Kingdom Palace for 60 minutes, Bailuzhou Park for 60 minutes, Qinhuai River for 120 minutes, Tomb of Ming Emperor Zhu Yuanzhang for 120 minutes.\n4. The daily opening_hours of spots can be obtained from the database table place. \"opening_hours_begin\" and \"opening_hours_end\" are the opening and closing times respectively\n5. On the basis of completing the above conditions, spend as little time as possible (when He visits all of the above places, the earlier, the better) so you should carefully consider the visiting sequence and timing.\n",
        "demands": {
            "TravelSimulator": {
                "begin_time": "2023-07-02 00:00",
                "end_time": "2023-07-03 00:00",
                "origin_city": "Nanjing",
                "origin_place": "Nanjing Railway Hotel",
                "budget": 99999,
                "check_opening_hours": true,
                "check_meal": false
            },
            "Constraints": {
                "SpotDurationConstraint": [
                    {
                        "spot": "Taiping Heavenly-Kingdom Palace",
                        "minutes": 60
                    },
                    {
                        "spot": "Bailuzhou Park",
                        "minutes": 60
                    },
                    {
                        "spot": "Qinhuai River",
                        "minutes": 120
                    },
                    {
                        "spot": "Tomb of Ming Emperor Zhu Yuanzhang",
                        "minutes": 120
                    }
                ]
            }
        },
        "type": 2
    },
    {
        "question": "Bob is going to play in Beijing, please make a visit plan for him.The demands are as follows:\n1. He lives in Beijing Railway Hotel. He needs to visit ['The Temple of Heaven', 'The Great Wall', 'Beijing Olympic Park', 'The Summer Palace'] and the order can be decided by you.\n2. one day(2023-07-02 7:00 ~ 2023-07-02 22:00) for this trip. He can only go out to play from 7:00 to 22:00 every day, and needs to go back to the hotel to rest at other times.\n3. Visit The Temple of Heaven for 120 minutes, The Great Wall for 60 minutes, Beijing Olympic Park for 90 minutes, The Summer Palace for 90 minutes.\n4. The daily opening_hours of spots can be obtained from the database table place. \"opening_hours_begin\" and \"opening_hours_end\" are the opening and closing times respectively\n5. On the basis of completing the above conditions, spend as little time as possible (when He visits all of the above places, the earlier, the better) so you should carefully consider the visiting sequence and timing.\n",
        "demands": {
            "TravelSimulator": {
                "begin_time": "2023-07-02 00:00",
                "end_time": "2023-07-03 00:00",
                "origin_city": "Beijing",
                "origin_place": "Beijing Railway Hotel",
                "budget": 99999,
                "check_opening_hours": true,
                "check_meal": false
            },
            "Constraints": {
                "SpotDurationConstraint": [
                    {
                        "spot": "The Temple of Heaven",
                        "minutes": 120
                    },
                    {
                        "spot": "The Great Wall",
                        "minutes": 60
                    },
                    {
                        "spot": "Beijing Olympic Park",
                        "minutes": 90
                    },
                    {
                        "spot": "The Summer Palace",
                        "minutes": 90
                    }
                ]
            }
        },
        "type": 2
    },
    {
        "question": "Bob is going to play in Hangzhou, please make a visit plan for him.The demands are as follows:\n1. He lives in Hangzhou Railway Hotel. He needs to visit ['Quaint Water Towns', 'Lingyin Temple', 'West Lake', 'China National Tea Museum'] and the order can be decided by you.\n2. one day(2023-07-09 7:00 ~ 2023-07-09 22:00) for this trip. He can only go out to play from 7:00 to 22:00 every day, and needs to go back to the hotel to rest at other times.\n3. Visit Quaint Water Towns for 90 minutes, Lingyin Temple for 60 minutes, West Lake for 90 minutes, China National Tea Museum for 120 minutes.\n4. 12:00 ~ 13:00 for lunch and  18:00 ~ 19:00 for dinner.\n5. Ignore the opening hours of attractions, assuming they are open all day\n6. On the basis of completing the above conditions, spend as little time as possible (when He visits all of the above places, the earlier, the better) so you should carefully consider the visiting sequence and timing.\n",
        "demands": {
            "TravelSimulator": {
                "begin_time": "2023-07-09 00:00",
                "end_time": "2023-07-10 00:00",
                "origin_city": "Hangzhou",
                "origin_place": "Hangzhou Railway Hotel",
                "budget": 99999,
                "check_opening_hours": false,
                "check_meal": true
            },
            "Constraints": {
                "SpotDurationConstraint": [
                    {
                        "spot": "Quaint Water Towns",
                        "minutes": 90
                    },
                    {
                        "spot": "Lingyin Temple",
                        "minutes": 60
                    },
                    {
                        "spot": "West Lake",
                        "minutes": 90
                    },
                    {
                        "spot": "China National Tea Museum",
                        "minutes": 120
                    }
                ]
            }
        },
        "type": 2
    },
    {
        "question": "Bob is going to play in Nanjing, please make a visit plan for him.The demands are as follows:\n1. He lives in Nanjing Railway Hotel. He needs to visit ['Qinhuai River', 'Taiping Heavenly-Kingdom Palace', 'Ming Palace', 'Tomb of Ming Emperor Zhu Yuanzhang'] and the order can be decided by you.\n2. one day(2023-07-07 7:00 ~ 2023-07-07 22:00) for this trip. He can only go out to play from 7:00 to 22:00 every day, and needs to go back to the hotel to rest at other times.\n3. Visit Qinhuai River for 120 minutes, Taiping Heavenly-Kingdom Palace for 120 minutes, Ming Palace for 120 minutes, Tomb of Ming Emperor Zhu Yuanzhang for 90 minutes.\n4. 12:00 ~ 13:00 for lunch and  18:00 ~ 19:00 for dinner.\n5. Ignore the opening hours of attractions, assuming they are open all day\n6. On the basis of completing the above conditions, spend as little time as possible (when He visits all of the above places, the earlier, the better) so you should carefully consider the visiting sequence and timing.\n",
        "demands": {
            "TravelSimulator": {
                "begin_time": "2023-07-07 00:00",
                "end_time": "2023-07-08 00:00",
                "origin_city": "Nanjing",
                "origin_place": "Nanjing Railway Hotel",
                "budget": 99999,
                "check_opening_hours": false,
                "check_meal": true
            },
            "Constraints": {
                "SpotDurationConstraint": [
                    {
                        "spot": "Qinhuai River",
                        "minutes": 120
                    },
                    {
                        "spot": "Taiping Heavenly-Kingdom Palace",
                        "minutes": 120
                    },
                    {
                        "spot": "Ming Palace",
                        "minutes": 120
                    },
                    {
                        "spot": "Tomb of Ming Emperor Zhu Yuanzhang",
                        "minutes": 90
                    }
                ]
            }
        },
        "type": 2
    },
    {
        "question": "Bob is going to play in Hangzhou, please make a visit plan for him.The demands are as follows:\n1. He lives in Hangzhou Railway Hotel. He needs to visit ['Quaint Water Towns', 'Lingyin Temple', 'Hefang Street', 'China National Tea Museum'] and the order can be decided by you.\n2. one day(2023-07-10 7:00 ~ 2023-07-10 22:00) for this trip. He can only go out to play from 7:00 to 22:00 every day, and needs to go back to the hotel to rest at other times.\n3. Visit Quaint Water Towns for 90 minutes, Lingyin Temple for 120 minutes, Hefang Street for 60 minutes, China National Tea Museum for 90 minutes.\n4. 12:00 ~ 13:00 for lunch and  18:00 ~ 19:00 for dinner.\n5. The daily opening_hours of spots can be obtained from the database table place. \"opening_hours_begin\" and \"opening_hours_end\" are the opening and closing times respectively\n6. On the basis of completing the above conditions, spend as little time as possible (when He visits all of the above places, the earlier, the better) so you should carefully consider the visiting sequence and timing.\n",
        "demands": {
            "TravelSimulator": {
                "begin_time": "2023-07-10 00:00",
                "end_time": "2023-07-11 00:00",
                "origin_city": "Hangzhou",
                "origin_place": "Hangzhou Railway Hotel",
                "budget": 99999,
                "check_opening_hours": true,
                "check_meal": true
            },
            "Constraints": {
                "SpotDurationConstraint": [
                    {
                        "spot": "Quaint Water Towns",
                        "minutes": 90
                    },
                    {
                        "spot": "Lingyin Temple",
                        "minutes": 120
                    },
                    {
                        "spot": "Hefang Street",
                        "minutes": 60
                    },
                    {
                        "spot": "China National Tea Museum",
                        "minutes": 90
                    }
                ]
            }
        },
        "type": 2
    },
    {
        "question": "Bob is going to play in Shanghai, please make a visit plan for him.The demands are as follows:\n1. He lives in Shanghai Railway Hotel. He needs to visit ['Qibao Ancient Town', 'Shanghai Disney', 'Shanghai Sightseeing Tunnel', 'Longhua Temple'] and the order can be decided by you.\n2. one day(2023-07-07 7:00 ~ 2023-07-07 22:00) for this trip. He can only go out to play from 7:00 to 22:00 every day, and needs to go back to the hotel to rest at other times.\n3. Visit Qibao Ancient Town for 120 minutes, Shanghai Disney for 120 minutes, Shanghai Sightseeing Tunnel for 120 minutes, Longhua Temple for 120 minutes.\n4. 12:00 ~ 13:00 for lunch and  18:00 ~ 19:00 for dinner.\n5. The daily opening_hours of spots can be obtained from the database table place. \"opening_hours_begin\" and \"opening_hours_end\" are the opening and closing times respectively\n6. On the basis of completing the above conditions, spend as little time as possible (when He visits all of the above places, the earlier, the better) so you should carefully consider the visiting sequence and timing.\n",
        "demands": {
            "TravelSimulator": {
                "begin_time": "2023-07-07 00:00",
                "end_time": "2023-07-08 00:00",
                "origin_city": "Shanghai",
                "origin_place": "Shanghai Railway Hotel",
                "budget": 99999,
                "check_opening_hours": true,
                "check_meal": true
            },
            "Constraints": {
                "SpotDurationConstraint": [
                    {
                        "spot": "Qibao Ancient Town",
                        "minutes": 120
                    },
                    {
                        "spot": "Shanghai Disney",
                        "minutes": 120
                    },
                    {
                        "spot": "Shanghai Sightseeing Tunnel",
                        "minutes": 120
                    },
                    {
                        "spot": "Longhua Temple",
                        "minutes": 120
                    }
                ]
            }
        },
        "type": 2
    },
    {
        "question": "Bob is going to play in Beijing, please make a visit plan for him.The demands are as follows:\n1. He lives in Beijing Railway Hotel. He needs to visit ['Shihua Cave', 'The Great Wall'] and the order can be decided by you.\n2. one day(2023-07-10 7:00 ~ 2023-07-10 22:00) for this trip. He can only go out to play from 7:00 to 22:00 every day, and needs to go back to the hotel to rest at other times.\n3. Visit Shihua Cave for 120 minutes, The Great Wall for 300 minutes.\n4. Ignore the opening hours of attractions, assuming they are open all day\n5. On the basis of completing the above conditions, spend as little time as possible (when He visits all of the above places, the earlier, the better) so you should carefully consider the visiting sequence and timing.\n",
        "demands": {
            "TravelSimulator": {
                "begin_time": "2023-07-10 00:00",
                "end_time": "2023-07-11 00:00",
                "origin_city": "Beijing",
                "origin_place": "Beijing Railway Hotel",
                "budget": 99999,
                "check_opening_hours": false,
                "check_meal": false
            },
            "Constraints": {
                "SpotDurationConstraint": [
                    {
                        "spot": "Shihua Cave",
                        "minutes": 120
                    },
                    {
                        "spot": "The Great Wall",
                        "minutes": 300
                    }
                ]
            }
        },
        "type": 2
    },
    {
        "question": "Bob is going to play in Shanghai, please make a visit plan for him.The demands are as follows:\n1. He lives in Shanghai Railway Hotel. He needs to visit ['Qibao Ancient Town', 'Shanghai History Museum'] and the order can be decided by you.\n2. one day(2023-07-09 7:00 ~ 2023-07-09 22:00) for this trip. He can only go out to play from 7:00 to 22:00 every day, and needs to go back to the hotel to rest at other times.\n3. Visit Qibao Ancient Town for 270 minutes, Shanghai History Museum for 120 minutes.\n4. Ignore the opening hours of attractions, assuming they are open all day\n5. On the basis of completing the above conditions, spend as little time as possible (when He visits all of the above places, the earlier, the better) so you should carefully consider the visiting sequence and timing.\n",
        "demands": {
            "TravelSimulator": {
                "begin_time": "2023-07-09 00:00",
                "end_time": "2023-07-10 00:00",
                "origin_city": "Shanghai",
                "origin_place": "Shanghai Railway Hotel",
                "budget": 99999,
                "check_opening_hours": false,
                "check_meal": false
            },
            "Constraints": {
                "SpotDurationConstraint": [
                    {
                        "spot": "Qibao Ancient Town",
                        "minutes": 270
                    },
                    {
                        "spot": "Shanghai History Museum",
                        "minutes": 120
                    }
                ]
            }
        },
        "type": 2
    },
    {
        "question": "Bob is going to play in Chengdu, please make a visit plan for him.The demands are as follows:\n1. He lives in Chengdu Railway Hotel. He needs to visit ['Chengdu Tea Houses', 'Du Fu Thatched Cottage'] and the order can be decided by you.\n2. one day(2023-07-11 7:00 ~ 2023-07-11 22:00) for this trip. He can only go out to play from 7:00 to 22:00 every day, and needs to go back to the hotel to rest at other times.\n3. Visit Chengdu Tea Houses for 240 minutes, Du Fu Thatched Cottage for 240 minutes.\n4. The daily opening_hours of spots can be obtained from the database table place. \"opening_hours_begin\" and \"opening_hours_end\" are the opening and closing times respectively\n5. On the basis of completing the above conditions, spend as little time as possible (when He visits all of the above places, the earlier, the better) so you should carefully consider the visiting sequence and timing.\n",
        "demands": {
            "TravelSimulator": {
                "begin_time": "2023-07-11 00:00",
                "end_time": "2023-07-12 00:00",
                "origin_city": "Chengdu",
                "origin_place": "Chengdu Railway Hotel",
                "budget": 99999,
                "check_opening_hours": true,
                "check_meal": false
            },
            "Constraints": {
                "SpotDurationConstraint": [
                    {
                        "spot": "Chengdu Tea Houses",
                        "minutes": 240
                    },
                    {
                        "spot": "Du Fu Thatched Cottage",
                        "minutes": 240
                    }
                ]
            }
        },
        "type": 2
    },
    {
        "question": "Bob is going to play in Chengdu, please make a visit plan for him.The demands are as follows:\n1. He lives in Chengdu Railway Hotel. He needs to visit ['Chengdu Panda Base', 'Leshan Giant Buddha'] and the order can be decided by you.\n2. one day(2023-07-10 7:00 ~ 2023-07-10 22:00) for this trip. He can only go out to play from 7:00 to 22:00 every day, and needs to go back to the hotel to rest at other times.\n3. Visit Chengdu Panda Base for 150 minutes, Leshan Giant Buddha for 120 minutes.\n4. The daily opening_hours of spots can be obtained from the database table place. \"opening_hours_begin\" and \"opening_hours_end\" are the opening and closing times respectively\n5. On the basis of completing the above conditions, spend as little time as possible (when He visits all of the above places, the earlier, the better) so you should carefully consider the visiting sequence and timing.\n",
        "demands": {
            "TravelSimulator": {
                "begin_time": "2023-07-10 00:00",
                "end_time": "2023-07-11 00:00",
                "origin_city": "Chengdu",
                "origin_place": "Chengdu Railway Hotel",
                "budget": 99999,
                "check_opening_hours": true,
                "check_meal": false
            },
            "Constraints": {
                "SpotDurationConstraint": [
                    {
                        "spot": "Chengdu Panda Base",
                        "minutes": 150
                    },
                    {
                        "spot": "Leshan Giant Buddha",
                        "minutes": 120
                    }
                ]
            }
        },
        "type": 2
    },
    {
        "question": "Bob is going to play in Wuhan, please make a visit plan for him.The demands are as follows:\n1. He lives in Wuhan Railway Hotel. He needs to visit ['Han Show', 'Tan Hua Lin'] and the order can be decided by you.\n2. one day(2023-07-10 7:00 ~ 2023-07-10 22:00) for this trip. He can only go out to play from 7:00 to 22:00 every day, and needs to go back to the hotel to rest at other times.\n3. Visit Han Show for 150 minutes, Tan Hua Lin for 210 minutes.\n4. 12:00 ~ 13:00 for lunch and  18:00 ~ 19:00 for dinner.\n5. Ignore the opening hours of attractions, assuming they are open all day\n6. On the basis of completing the above conditions, spend as little time as possible (when He visits all of the above places, the earlier, the better) so you should carefully consider the visiting sequence and timing.\n",
        "demands": {
            "TravelSimulator": {
                "begin_time": "2023-07-10 00:00",
                "end_time": "2023-07-11 00:00",
                "origin_city": "Wuhan",
                "origin_place": "Wuhan Railway Hotel",
                "budget": 99999,
                "check_opening_hours": false,
                "check_meal": true
            },
            "Constraints": {
                "SpotDurationConstraint": [
                    {
                        "spot": "Han Show",
                        "minutes": 150
                    },
                    {
                        "spot": "Tan Hua Lin",
                        "minutes": 210
                    }
                ]
            }
        },
        "type": 2
    },
    {
        "question": "Bob is going to play in Hangzhou, please make a visit plan for him.The demands are as follows:\n1. He lives in Hangzhou Railway Hotel. He needs to visit ['Lingyin Temple', 'Hefang Street'] and the order can be decided by you.\n2. one day(2023-07-09 7:00 ~ 2023-07-09 22:00) for this trip. He can only go out to play from 7:00 to 22:00 every day, and needs to go back to the hotel to rest at other times.\n3. Visit Lingyin Temple for 180 minutes, Hefang Street for 270 minutes.\n4. 12:00 ~ 13:00 for lunch and  18:00 ~ 19:00 for dinner.\n5. Ignore the opening hours of attractions, assuming they are open all day\n6. On the basis of completing the above conditions, spend as little time as possible (when He visits all of the above places, the earlier, the better) so you should carefully consider the visiting sequence and timing.\n",
        "demands": {
            "TravelSimulator": {
                "begin_time": "2023-07-09 00:00",
                "end_time": "2023-07-10 00:00",
                "origin_city": "Hangzhou",
                "origin_place": "Hangzhou Railway Hotel",
                "budget": 99999,
                "check_opening_hours": false,
                "check_meal": true
            },
            "Constraints": {
                "SpotDurationConstraint": [
                    {
                        "spot": "Lingyin Temple",
                        "minutes": 180
                    },
                    {
                        "spot": "Hefang Street",
                        "minutes": 270
                    }
                ]
            }
        },
        "type": 2
    },
    {
        "question": "Bob is going to play in Hangzhou, please make a visit plan for him.The demands are as follows:\n1. He lives in Hangzhou Railway Hotel. He needs to visit ['Hefang Street', 'West Lake'] and the order can be decided by you.\n2. one day(2023-07-08 7:00 ~ 2023-07-08 22:00) for this trip. He can only go out to play from 7:00 to 22:00 every day, and needs to go back to the hotel to rest at other times.\n3. Visit Hefang Street for 300 minutes, West Lake for 300 minutes.\n4. 12:00 ~ 13:00 for lunch and  18:00 ~ 19:00 for dinner.\n5. The daily opening_hours of spots can be obtained from the database table place. \"opening_hours_begin\" and \"opening_hours_end\" are the opening and closing times respectively\n6. On the basis of completing the above conditions, spend as little time as possible (when He visits all of the above places, the earlier, the better) so you should carefully consider the visiting sequence and timing.\n",
        "demands": {
            "TravelSimulator": {
                "begin_time": "2023-07-08 00:00",
                "end_time": "2023-07-09 00:00",
                "origin_city": "Hangzhou",
                "origin_place": "Hangzhou Railway Hotel",
                "budget": 99999,
                "check_opening_hours": true,
                "check_meal": true
            },
            "Constraints": {
                "SpotDurationConstraint": [
                    {
                        "spot": "Hefang Street",
                        "minutes": 300
                    },
                    {
                        "spot": "West Lake",
                        "minutes": 300
                    }
                ]
            }
        },
        "type": 2
    },
    {
        "question": "Bob is going to play in Wuhan, please make a visit plan for him.The demands are as follows:\n1. He lives in Wuhan Railway Hotel. He needs to visit ['Hubu Alley', 'Tan Hua Lin'] and the order can be decided by you.\n2. one day(2023-07-04 7:00 ~ 2023-07-04 22:00) for this trip. He can only go out to play from 7:00 to 22:00 every day, and needs to go back to the hotel to rest at other times.\n3. Visit Hubu Alley for 240 minutes, Tan Hua Lin for 300 minutes.\n4. 12:00 ~ 13:00 for lunch and  18:00 ~ 19:00 for dinner.\n5. The daily opening_hours of spots can be obtained from the database table place. \"opening_hours_begin\" and \"opening_hours_end\" are the opening and closing times respectively\n6. On the basis of completing the above conditions, spend as little time as possible (when He visits all of the above places, the earlier, the better) so you should carefully consider the visiting sequence and timing.\n",
        "demands": {
            "TravelSimulator": {
                "begin_time": "2023-07-04 00:00",
                "end_time": "2023-07-05 00:00",
                "origin_city": "Wuhan",
                "origin_place": "Wuhan Railway Hotel",
                "budget": 99999,
                "check_opening_hours": true,
                "check_meal": true
            },
            "Constraints": {
                "SpotDurationConstraint": [
                    {
                        "spot": "Hubu Alley",
                        "minutes": 240
                    },
                    {
                        "spot": "Tan Hua Lin",
                        "minutes": 300
                    }
                ]
            }
        },
        "type": 2
    },
    {
        "question": "Bob is going to play in Hangzhou, please make a visit plan for him.The demands are as follows:\n1. He lives in Hangzhou Railway Hotel. He needs to visit ['China National Tea Museum', 'West Lake', 'Hefang Street', 'Lingyin Temple'] and the order can be decided by you.\n2. 2 days(2023-07-08 00:00 ~ 2023-07-10 00:00) for this trip. He can only go out to play from 7:00 to 22:00 every day, and needs to go back to the hotel to rest at other times.\n3. Visit China National Tea Museum for 150 minutes, West Lake for 120 minutes, Hefang Street for 270 minutes, Lingyin Temple for 150 minutes.\n4. Ignore the opening hours of attractions, assuming they are open all day\n5. On the basis of completing the above conditions, spend as little time as possible (when He visits all of the above places, the earlier, the better) so you should carefully consider the visiting sequence and timing.\n",
        "demands": {
            "TravelSimulator": {
                "begin_time": "2023-07-08 00:00",
                "end_time": "2023-07-10 00:00",
                "origin_city": "Hangzhou",
                "origin_place": "Hangzhou Railway Hotel",
                "budget": 99999,
                "check_opening_hours": false,
                "check_meal": false
            },
            "Constraints": {
                "SpotDurationConstraint": [
                    {
                        "spot": "China National Tea Museum",
                        "minutes": 150
                    },
                    {
                        "spot": "West Lake",
                        "minutes": 120
                    },
                    {
                        "spot": "Hefang Street",
                        "minutes": 270
                    },
                    {
                        "spot": "Lingyin Temple",
                        "minutes": 150
                    }
                ]
            }
        },
        "type": 2
    },
    {
        "question": "Bob is going to play in Chengdu, please make a visit plan for him.The demands are as follows:\n1. He lives in Chengdu Railway Hotel. He needs to visit ['Leshan Giant Buddha', 'The Chengdu Wuhou Shrine', 'Du Fu Thatched Cottage', 'Chengdu Tea Houses'] and the order can be decided by you.\n2. 2 days(2023-07-10 00:00 ~ 2023-07-12 00:00) for this trip. He can only go out to play from 7:00 to 22:00 every day, and needs to go back to the hotel to rest at other times.\n3. Visit Leshan Giant Buddha for 210 minutes, The Chengdu Wuhou Shrine for 150 minutes, Du Fu Thatched Cottage for 240 minutes, Chengdu Tea Houses for 270 minutes.\n4. Ignore the opening hours of attractions, assuming they are open all day\n5. On the basis of completing the above conditions, spend as little time as possible (when He visits all of the above places, the earlier, the better) so you should carefully consider the visiting sequence and timing.\n",
        "demands": {
            "TravelSimulator": {
                "begin_time": "2023-07-10 00:00",
                "end_time": "2023-07-12 00:00",
                "origin_city": "Chengdu",
                "origin_place": "Chengdu Railway Hotel",
                "budget": 99999,
                "check_opening_hours": false,
                "check_meal": false
            },
            "Constraints": {
                "SpotDurationConstraint": [
                    {
                        "spot": "Leshan Giant Buddha",
                        "minutes": 210
                    },
                    {
                        "spot": "The Chengdu Wuhou Shrine",
                        "minutes": 150
                    },
                    {
                        "spot": "Du Fu Thatched Cottage",
                        "minutes": 240
                    },
                    {
                        "spot": "Chengdu Tea Houses",
                        "minutes": 270
                    }
                ]
            }
        },
        "type": 2
    },
    {
        "question": "Bob is going to play in Beijing, please make a visit plan for him.The demands are as follows:\n1. He lives in Beijing Railway Hotel. He needs to visit ['The Temple of Heaven', 'The Great Wall', 'Beijing Stone Carvings Art Museum', 'Tiananmen Square'] and the order can be decided by you.\n2. 2 days(2023-07-08 00:00 ~ 2023-07-10 00:00) for this trip. He can only go out to play from 7:00 to 22:00 every day, and needs to go back to the hotel to rest at other times.\n3. Visit The Temple of Heaven for 120 minutes, The Great Wall for 270 minutes, Beijing Stone Carvings Art Museum for 180 minutes, Tiananmen Square for 150 minutes.\n4. The daily opening_hours of spots can be obtained from the database table place. \"opening_hours_begin\" and \"opening_hours_end\" are the opening and closing times respectively\n5. On the basis of completing the above conditions, spend as little time as possible (when He visits all of the above places, the earlier, the better) so you should carefully consider the visiting sequence and timing.\n",
        "demands": {
            "TravelSimulator": {
                "begin_time": "2023-07-08 00:00",
                "end_time": "2023-07-10 00:00",
                "origin_city": "Beijing",
                "origin_place": "Beijing Railway Hotel",
                "budget": 99999,
                "check_opening_hours": true,
                "check_meal": false
            },
            "Constraints": {
                "SpotDurationConstraint": [
                    {
                        "spot": "The Temple of Heaven",
                        "minutes": 120
                    },
                    {
                        "spot": "The Great Wall",
                        "minutes": 270
                    },
                    {
                        "spot": "Beijing Stone Carvings Art Museum",
                        "minutes": 180
                    },
                    {
                        "spot": "Tiananmen Square",
                        "minutes": 150
                    }
                ]
            }
        },
        "type": 2
    },
    {
        "question": "Bob is going to play in Shanghai, please make a visit plan for him.The demands are as follows:\n1. He lives in Shanghai Railway Hotel. He needs to visit ['Xintiandi', 'Shanghai History Museum', 'Century Park', 'Shanghai Sightseeing Tunnel'] and the order can be decided by you.\n2. 2 days(2023-07-06 00:00 ~ 2023-07-08 00:00) for this trip. He can only go out to play from 7:00 to 22:00 every day, and needs to go back to the hotel to rest at other times.\n3. Visit Xintiandi for 180 minutes, Shanghai History Museum for 270 minutes, Century Park for 150 minutes, Shanghai Sightseeing Tunnel for 210 minutes.\n4. The daily opening_hours of spots can be obtained from the database table place. \"opening_hours_begin\" and \"opening_hours_end\" are the opening and closing times respectively\n5. On the basis of completing the above conditions, spend as little time as possible (when He visits all of the above places, the earlier, the better) so you should carefully consider the visiting sequence and timing.\n",
        "demands": {
            "TravelSimulator": {
                "begin_time": "2023-07-06 00:00",
                "end_time": "2023-07-08 00:00",
                "origin_city": "Shanghai",
                "origin_place": "Shanghai Railway Hotel",
                "budget": 99999,
                "check_opening_hours": true,
                "check_meal": false
            },
            "Constraints": {
                "SpotDurationConstraint": [
                    {
                        "spot": "Xintiandi",
                        "minutes": 180
                    },
                    {
                        "spot": "Shanghai History Museum",
                        "minutes": 270
                    },
                    {
                        "spot": "Century Park",
                        "minutes": 150
                    },
                    {
                        "spot": "Shanghai Sightseeing Tunnel",
                        "minutes": 210
                    }
                ]
            }
        },
        "type": 2
    },
    {
        "question": "Bob is going to play in Hangzhou, please make a visit plan for him.The demands are as follows:\n1. He lives in Hangzhou Railway Hotel. He needs to visit ['Lingyin Temple', 'Quaint Water Towns', 'West Lake', 'Hefang Street'] and the order can be decided by you.\n2. 2 days(2023-07-11 00:00 ~ 2023-07-13 00:00) for this trip. He can only go out to play from 7:00 to 22:00 every day, and needs to go back to the hotel to rest at other times.\n3. Visit Lingyin Temple for 300 minutes, Quaint Water Towns for 150 minutes, West Lake for 240 minutes, Hefang Street for 210 minutes.\n4. 12:00 ~ 13:00 for lunch and  18:00 ~ 19:00 for dinner.\n5. Ignore the opening hours of attractions, assuming they are open all day\n6. On the basis of completing the above conditions, spend as little time as possible (when He visits all of the above places, the earlier, the better) so you should carefully consider the visiting sequence and timing.\n",
        "demands": {
            "TravelSimulator": {
                "begin_time": "2023-07-11 00:00",
                "end_time": "2023-07-13 00:00",
                "origin_city": "Hangzhou",
                "origin_place": "Hangzhou Railway Hotel",
                "budget": 99999,
                "check_opening_hours": false,
                "check_meal": true
            },
            "Constraints": {
                "SpotDurationConstraint": [
                    {
                        "spot": "Lingyin Temple",
                        "minutes": 300
                    },
                    {
                        "spot": "Quaint Water Towns",
                        "minutes": 150
                    },
                    {
                        "spot": "West Lake",
                        "minutes": 240
                    },
                    {
                        "spot": "Hefang Street",
                        "minutes": 210
                    }
                ]
            }
        },
        "type": 2
    },
    {
        "question": "Bob is going to play in Shanghai, please make a visit plan for him.The demands are as follows:\n1. He lives in Shanghai Railway Hotel. He needs to visit ['Xintiandi', 'Shanghai Disney', 'Longhua Temple', 'Shanghai History Museum'] and the order can be decided by you.\n2. 2 days(2023-07-03 00:00 ~ 2023-07-05 00:00) for this trip. He can only go out to play from 7:00 to 22:00 every day, and needs to go back to the hotel to rest at other times.\n3. Visit Xintiandi for 150 minutes, Shanghai Disney for 240 minutes, Longhua Temple for 270 minutes, Shanghai History Museum for 210 minutes.\n4. 12:00 ~ 13:00 for lunch and  18:00 ~ 19:00 for dinner.\n5. Ignore the opening hours of attractions, assuming they are open all day\n6. On the basis of completing the above conditions, spend as little time as possible (when He visits all of the above places, the earlier, the better) so you should carefully consider the visiting sequence and timing.\n",
        "demands": {
            "TravelSimulator": {
                "begin_time": "2023-07-03 00:00",
                "end_time": "2023-07-05 00:00",
                "origin_city": "Shanghai",
                "origin_place": "Shanghai Railway Hotel",
                "budget": 99999,
                "check_opening_hours": false,
                "check_meal": true
            },
            "Constraints": {
                "SpotDurationConstraint": [
                    {
                        "spot": "Xintiandi",
                        "minutes": 150
                    },
                    {
                        "spot": "Shanghai Disney",
                        "minutes": 240
                    },
                    {
                        "spot": "Longhua Temple",
                        "minutes": 270
                    },
                    {
                        "spot": "Shanghai History Museum",
                        "minutes": 210
                    }
                ]
            }
        },
        "type": 2
    },
    {
        "question": "Bob is going to play in Hangzhou, please make a visit plan for him.The demands are as follows:\n1. He lives in Hangzhou Railway Hotel. He needs to visit ['Quaint Water Towns', 'China National Tea Museum', 'West Lake', 'Hefang Street'] and the order can be decided by you.\n2. 2 days(2023-07-06 00:00 ~ 2023-07-08 00:00) for this trip. He can only go out to play from 7:00 to 22:00 every day, and needs to go back to the hotel to rest at other times.\n3. Visit Quaint Water Towns for 240 minutes, China National Tea Museum for 210 minutes, West Lake for 120 minutes, Hefang Street for 180 minutes.\n4. 12:00 ~ 13:00 for lunch and  18:00 ~ 19:00 for dinner.\n5. The daily opening_hours of spots can be obtained from the database table place. \"opening_hours_begin\" and \"opening_hours_end\" are the opening and closing times respectively\n6. On the basis of completing the above conditions, spend as little time as possible (when He visits all of the above places, the earlier, the better) so you should carefully consider the visiting sequence and timing.\n",
        "demands": {
            "TravelSimulator": {
                "begin_time": "2023-07-06 00:00",
                "end_time": "2023-07-08 00:00",
                "origin_city": "Hangzhou",
                "origin_place": "Hangzhou Railway Hotel",
                "budget": 99999,
                "check_opening_hours": true,
                "check_meal": true
            },
            "Constraints": {
                "SpotDurationConstraint": [
                    {
                        "spot": "Quaint Water Towns",
                        "minutes": 240
                    },
                    {
                        "spot": "China National Tea Museum",
                        "minutes": 210
                    },
                    {
                        "spot": "West Lake",
                        "minutes": 120
                    },
                    {
                        "spot": "Hefang Street",
                        "minutes": 180
                    }
                ]
            }
        },
        "type": 2
    },
    {
        "question": "Bob is going to play in Hangzhou, please make a visit plan for him.The demands are as follows:\n1. He lives in Hangzhou Railway Hotel. He needs to visit ['China National Tea Museum', 'Lingyin Temple', 'West Lake', 'Hefang Street'] and the order can be decided by you.\n2. 2 days(2023-07-05 00:00 ~ 2023-07-07 00:00) for this trip. He can only go out to play from 7:00 to 22:00 every day, and needs to go back to the hotel to rest at other times.\n3. Visit China National Tea Museum for 300 minutes, Lingyin Temple for 180 minutes, West Lake for 300 minutes, Hefang Street for 240 minutes.\n4. 12:00 ~ 13:00 for lunch and  18:00 ~ 19:00 for dinner.\n5. The daily opening_hours of spots can be obtained from the database table place. \"opening_hours_begin\" and \"opening_hours_end\" are the opening and closing times respectively\n6. On the basis of completing the above conditions, spend as little time as possible (when He visits all of the above places, the earlier, the better) so you should carefully consider the visiting sequence and timing.\n",
        "demands": {
            "TravelSimulator": {
                "begin_time": "2023-07-05 00:00",
                "end_time": "2023-07-07 00:00",
                "origin_city": "Hangzhou",
                "origin_place": "Hangzhou Railway Hotel",
                "budget": 99999,
                "check_opening_hours": true,
                "check_meal": true
            },
            "Constraints": {
                "SpotDurationConstraint": [
                    {
                        "spot": "China National Tea Museum",
                        "minutes": 300
                    },
                    {
                        "spot": "Lingyin Temple",
                        "minutes": 180
                    },
                    {
                        "spot": "West Lake",
                        "minutes": 300
                    },
                    {
                        "spot": "Hefang Street",
                        "minutes": 240
                    }
                ]
            }
        },
        "type": 2
    },
    {
        "question": "Bob is going to play in Shanghai, please make a visit plan for him.The demands are as follows:\n1. He lives in Shanghai Railway Hotel. He needs to visit ['Huangpu River Cruise', 'Shanghai Sightseeing Tunnel', 'Xintiandi', 'Shanghai Disney', 'Shanghai History Museum', 'Century Park'] and the order can be decided by you.\n2. 3 days(2023-07-10 00:00 ~ 2023-07-13 00:00) for this trip. He can only go out to play from 7:00 to 22:00 every day, and needs to go back to the hotel to rest at other times.\n3. Visit Huangpu River Cruise for 210 minutes, Shanghai Sightseeing Tunnel for 300 minutes, Xintiandi for 240 minutes, Shanghai Disney for 150 minutes, Shanghai History Museum for 120 minutes, Century Park for 270 minutes.\n4. Ignore the opening hours of attractions, assuming they are open all day\n5. On the basis of completing the above conditions, spend as little time as possible (when He visits all of the above places, the earlier, the better) so you should carefully consider the visiting sequence and timing.\n",
        "demands": {
            "TravelSimulator": {
                "begin_time": "2023-07-10 00:00",
                "end_time": "2023-07-13 00:00",
                "origin_city": "Shanghai",
                "origin_place": "Shanghai Railway Hotel",
                "budget": 99999,
                "check_opening_hours": false,
                "check_meal": false
            },
            "Constraints": {
                "SpotDurationConstraint": [
                    {
                        "spot": "Huangpu River Cruise",
                        "minutes": 210
                    },
                    {
                        "spot": "Shanghai Sightseeing Tunnel",
                        "minutes": 300
                    },
                    {
                        "spot": "Xintiandi",
                        "minutes": 240
                    },
                    {
                        "spot": "Shanghai Disney",
                        "minutes": 150
                    },
                    {
                        "spot": "Shanghai History Museum",
                        "minutes": 120
                    },
                    {
                        "spot": "Century Park",
                        "minutes": 270
                    }
                ]
            }
        },
        "type": 2
    },
    {
        "question": "Bob is going to play in Beijing, please make a visit plan for him.The demands are as follows:\n1. He lives in Beijing Railway Hotel. He needs to visit ['Beijing Olympic Park', 'Shihua Cave', 'The Temple of Heaven', 'The Great Wall', 'Beijing Stone Carvings Art Museum', 'The Summer Palace'] and the order can be decided by you.\n2. 3 days(2023-07-07 00:00 ~ 2023-07-10 00:00) for this trip. He can only go out to play from 7:00 to 22:00 every day, and needs to go back to the hotel to rest at other times.\n3. Visit Beijing Olympic Park for 240 minutes, Shihua Cave for 240 minutes, The Temple of Heaven for 300 minutes, The Great Wall for 180 minutes, Beijing Stone Carvings Art Museum for 180 minutes, The Summer Palace for 180 minutes.\n4. Ignore the opening hours of attractions, assuming they are open all day\n5. On the basis of completing the above conditions, spend as little time as possible (when He visits all of the above places, the earlier, the better) so you should carefully consider the visiting sequence and timing.\n",
        "demands": {
            "TravelSimulator": {
                "begin_time": "2023-07-07 00:00",
                "end_time": "2023-07-10 00:00",
                "origin_city": "Beijing",
                "origin_place": "Beijing Railway Hotel",
                "budget": 99999,
                "check_opening_hours": false,
                "check_meal": false
            },
            "Constraints": {
                "SpotDurationConstraint": [
                    {
                        "spot": "Beijing Olympic Park",
                        "minutes": 240
                    },
                    {
                        "spot": "Shihua Cave",
                        "minutes": 240
                    },
                    {
                        "spot": "The Temple of Heaven",
                        "minutes": 300
                    },
                    {
                        "spot": "The Great Wall",
                        "minutes": 180
                    },
                    {
                        "spot": "Beijing Stone Carvings Art Museum",
                        "minutes": 180
                    },
                    {
                        "spot": "The Summer Palace",
                        "minutes": 180
                    }
                ]
            }
        },
        "type": 2
    },
    {
        "question": "Bob is going to play in Beijing, please make a visit plan for him.The demands are as follows:\n1. He lives in Beijing Railway Hotel. He needs to visit ['Beijing Stone Carvings Art Museum', 'Beijing Olympic Park', 'Shihua Cave', 'The Summer Palace', 'The Temple of Heaven', 'Tiananmen Square'] and the order can be decided by you.\n2. 3 days(2023-07-10 00:00 ~ 2023-07-13 00:00) for this trip. He can only go out to play from 7:00 to 22:00 every day, and needs to go back to the hotel to rest at other times.\n3. Visit Beijing Stone Carvings Art Museum for 300 minutes, Beijing Olympic Park for 120 minutes, Shihua Cave for 180 minutes, The Summer Palace for 120 minutes, The Temple of Heaven for 210 minutes, Tiananmen Square for 120 minutes.\n4. The daily opening_hours of spots can be obtained from the database table place. \"opening_hours_begin\" and \"opening_hours_end\" are the opening and closing times respectively\n5. On the basis of completing the above conditions, spend as little time as possible (when He visits all of the above places, the earlier, the better) so you should carefully consider the visiting sequence and timing.\n",
        "demands": {
            "TravelSimulator": {
                "begin_time": "2023-07-10 00:00",
                "end_time": "2023-07-13 00:00",
                "origin_city": "Beijing",
                "origin_place": "Beijing Railway Hotel",
                "budget": 99999,
                "check_opening_hours": true,
                "check_meal": false
            },
            "Constraints": {
                "SpotDurationConstraint": [
                    {
                        "spot": "Beijing Stone Carvings Art Museum",
                        "minutes": 300
                    },
                    {
                        "spot": "Beijing Olympic Park",
                        "minutes": 120
                    },
                    {
                        "spot": "Shihua Cave",
                        "minutes": 180
                    },
                    {
                        "spot": "The Summer Palace",
                        "minutes": 120
                    },
                    {
                        "spot": "The Temple of Heaven",
                        "minutes": 210
                    },
                    {
                        "spot": "Tiananmen Square",
                        "minutes": 120
                    }
                ]
            }
        },
        "type": 2
    },
    {
        "question": "Bob is going to play in Wuhan, please make a visit plan for him.The demands are as follows:\n1. He lives in Wuhan Railway Hotel. He needs to visit ['Han Show', 'Hubu Alley', 'Baotong Temple', 'Yellow Crane Tower', 'Tan Hua Lin', 'East Lake'] and the order can be decided by you.\n2. 3 days(2023-07-11 00:00 ~ 2023-07-14 00:00) for this trip. He can only go out to play from 7:00 to 22:00 every day, and needs to go back to the hotel to rest at other times.\n3. Visit Han Show for 240 minutes, Hubu Alley for 150 minutes, Baotong Temple for 240 minutes, Yellow Crane Tower for 120 minutes, Tan Hua Lin for 180 minutes, East Lake for 180 minutes.\n4. The daily opening_hours of spots can be obtained from the database table place. \"opening_hours_begin\" and \"opening_hours_end\" are the opening and closing times respectively\n5. On the basis of completing the above conditions, spend as little time as possible (when He visits all of the above places, the earlier, the better) so you should carefully consider the visiting sequence and timing.\n",
        "demands": {
            "TravelSimulator": {
                "begin_time": "2023-07-11 00:00",
                "end_time": "2023-07-14 00:00",
                "origin_city": "Wuhan",
                "origin_place": "Wuhan Railway Hotel",
                "budget": 99999,
                "check_opening_hours": true,
                "check_meal": false
            },
            "Constraints": {
                "SpotDurationConstraint": [
                    {
                        "spot": "Han Show",
                        "minutes": 240
                    },
                    {
                        "spot": "Hubu Alley",
                        "minutes": 150
                    },
                    {
                        "spot": "Baotong Temple",
                        "minutes": 240
                    },
                    {
                        "spot": "Yellow Crane Tower",
                        "minutes": 120
                    },
                    {
                        "spot": "Tan Hua Lin",
                        "minutes": 180
                    },
                    {
                        "spot": "East Lake",
                        "minutes": 180
                    }
                ]
            }
        },
        "type": 2
    },
    {
        "question": "Bob is going to play in Beijing, please make a visit plan for him.The demands are as follows:\n1. He lives in Beijing Railway Hotel. He needs to visit ['Shihua Cave', 'Tiananmen Square', 'The Forbidden City', 'The Great Wall', 'The Temple of Heaven', 'Beijing Stone Carvings Art Museum'] and the order can be decided by you.\n2. 3 days(2023-07-11 00:00 ~ 2023-07-14 00:00) for this trip. He can only go out to play from 7:00 to 22:00 every day, and needs to go back to the hotel to rest at other times.\n3. Visit Shihua Cave for 270 minutes, Tiananmen Square for 120 minutes, The Forbidden City for 120 minutes, The Great Wall for 210 minutes, The Temple of Heaven for 120 minutes, Beijing Stone Carvings Art Museum for 300 minutes.\n4. 12:00 ~ 13:00 for lunch and  18:00 ~ 19:00 for dinner.\n5. Ignore the opening hours of attractions, assuming they are open all day\n6. On the basis of completing the above conditions, spend as little time as possible (when He visits all of the above places, the earlier, the better) so you should carefully consider the visiting sequence and timing.\n",
        "demands": {
            "TravelSimulator": {
                "begin_time": "2023-07-11 00:00",
                "end_time": "2023-07-14 00:00",
                "origin_city": "Beijing",
                "origin_place": "Beijing Railway Hotel",
                "budget": 99999,
                "check_opening_hours": false,
                "check_meal": true
            },
            "Constraints": {
                "SpotDurationConstraint": [
                    {
                        "spot": "Shihua Cave",
                        "minutes": 270
                    },
                    {
                        "spot": "Tiananmen Square",
                        "minutes": 120
                    },
                    {
                        "spot": "The Forbidden City",
                        "minutes": 120
                    },
                    {
                        "spot": "The Great Wall",
                        "minutes": 210
                    },
                    {
                        "spot": "The Temple of Heaven",
                        "minutes": 120
                    },
                    {
                        "spot": "Beijing Stone Carvings Art Museum",
                        "minutes": 300
                    }
                ]
            }
        },
        "type": 2
    },
    {
        "question": "Bob is going to play in Wuhan, please make a visit plan for him.The demands are as follows:\n1. He lives in Wuhan Railway Hotel. He needs to visit ['Yellow Crane Tower', 'Han Show', 'Tan Hua Lin', 'Baotong Temple', 'East Lake', 'Hubu Alley'] and the order can be decided by you.\n2. 3 days(2023-07-03 00:00 ~ 2023-07-06 00:00) for this trip. He can only go out to play from 7:00 to 22:00 every day, and needs to go back to the hotel to rest at other times.\n3. Visit Yellow Crane Tower for 210 minutes, Han Show for 150 minutes, Tan Hua Lin for 270 minutes, Baotong Temple for 150 minutes, East Lake for 150 minutes, Hubu Alley for 270 minutes.\n4. 12:00 ~ 13:00 for lunch and  18:00 ~ 19:00 for dinner.\n5. Ignore the opening hours of attractions, assuming they are open all day\n6. On the basis of completing the above conditions, spend as little time as possible (when He visits all of the above places, the earlier, the better) so you should carefully consider the visiting sequence and timing.\n",
        "demands": {
            "TravelSimulator": {
                "begin_time": "2023-07-03 00:00",
                "end_time": "2023-07-06 00:00",
                "origin_city": "Wuhan",
                "origin_place": "Wuhan Railway Hotel",
                "budget": 99999,
                "check_opening_hours": false,
                "check_meal": true
            },
            "Constraints": {
                "SpotDurationConstraint": [
                    {
                        "spot": "Yellow Crane Tower",
                        "minutes": 210
                    },
                    {
                        "spot": "Han Show",
                        "minutes": 150
                    },
                    {
                        "spot": "Tan Hua Lin",
                        "minutes": 270
                    },
                    {
                        "spot": "Baotong Temple",
                        "minutes": 150
                    },
                    {
                        "spot": "East Lake",
                        "minutes": 150
                    },
                    {
                        "spot": "Hubu Alley",
                        "minutes": 270
                    }
                ]
            }
        },
        "type": 2
    },
    {
        "question": "Bob is going to play in Wuhan, please make a visit plan for him.The demands are as follows:\n1. He lives in Wuhan Railway Hotel. He needs to visit ['Yellow Crane Tower', 'East Lake', 'Tan Hua Lin', 'Baotong Temple', 'Han Show', 'Hubu Alley'] and the order can be decided by you.\n2. 3 days(2023-07-09 00:00 ~ 2023-07-12 00:00) for this trip. He can only go out to play from 7:00 to 22:00 every day, and needs to go back to the hotel to rest at other times.\n3. Visit Yellow Crane Tower for 180 minutes, East Lake for 120 minutes, Tan Hua Lin for 150 minutes, Baotong Temple for 270 minutes, Han Show for 180 minutes, Hubu Alley for 120 minutes.\n4. 12:00 ~ 13:00 for lunch and  18:00 ~ 19:00 for dinner.\n5. The daily opening_hours of spots can be obtained from the database table place. \"opening_hours_begin\" and \"opening_hours_end\" are the opening and closing times respectively\n6. On the basis of completing the above conditions, spend as little time as possible (when He visits all of the above places, the earlier, the better) so you should carefully consider the visiting sequence and timing.\n",
        "demands": {
            "TravelSimulator": {
                "begin_time": "2023-07-09 00:00",
                "end_time": "2023-07-12 00:00",
                "origin_city": "Wuhan",
                "origin_place": "Wuhan Railway Hotel",
                "budget": 99999,
                "check_opening_hours": true,
                "check_meal": true
            },
            "Constraints": {
                "SpotDurationConstraint": [
                    {
                        "spot": "Yellow Crane Tower",
                        "minutes": 180
                    },
                    {
                        "spot": "East Lake",
                        "minutes": 120
                    },
                    {
                        "spot": "Tan Hua Lin",
                        "minutes": 150
                    },
                    {
                        "spot": "Baotong Temple",
                        "minutes": 270
                    },
                    {
                        "spot": "Han Show",
                        "minutes": 180
                    },
                    {
                        "spot": "Hubu Alley",
                        "minutes": 120
                    }
                ]
            }
        },
        "type": 2
    },
    {
        "question": "Bob is going to play in Beijing, please make a visit plan for him.The demands are as follows:\n1. He lives in Beijing Railway Hotel. He needs to visit ['The Forbidden City', 'The Temple of Heaven', 'Tiananmen Square', 'Beijing Stone Carvings Art Museum', 'The Great Wall', 'Beijing Olympic Park'] and the order can be decided by you.\n2. 3 days(2023-07-08 00:00 ~ 2023-07-11 00:00) for this trip. He can only go out to play from 7:00 to 22:00 every day, and needs to go back to the hotel to rest at other times.\n3. Visit The Forbidden City for 180 minutes, The Temple of Heaven for 210 minutes, Tiananmen Square for 120 minutes, Beijing Stone Carvings Art Museum for 120 minutes, The Great Wall for 180 minutes, Beijing Olympic Park for 240 minutes.\n4. 12:00 ~ 13:00 for lunch and  18:00 ~ 19:00 for dinner.\n5. The daily opening_hours of spots can be obtained from the database table place. \"opening_hours_begin\" and \"opening_hours_end\" are the opening and closing times respectively\n6. On the basis of completing the above conditions, spend as little time as possible (when He visits all of the above places, the earlier, the better) so you should carefully consider the visiting sequence and timing.\n",
        "demands": {
            "TravelSimulator": {
                "begin_time": "2023-07-08 00:00",
                "end_time": "2023-07-11 00:00",
                "origin_city": "Beijing",
                "origin_place": "Beijing Railway Hotel",
                "budget": 99999,
                "check_opening_hours": true,
                "check_meal": true
            },
            "Constraints": {
                "SpotDurationConstraint": [
                    {
                        "spot": "The Forbidden City",
                        "minutes": 180
                    },
                    {
                        "spot": "The Temple of Heaven",
                        "minutes": 210
                    },
                    {
                        "spot": "Tiananmen Square",
                        "minutes": 120
                    },
                    {
                        "spot": "Beijing Stone Carvings Art Museum",
                        "minutes": 120
                    },
                    {
                        "spot": "The Great Wall",
                        "minutes": 180
                    },
                    {
                        "spot": "Beijing Olympic Park",
                        "minutes": 240
                    }
                ]
            }
        },
        "type": 2
    }
]